{"last_tab":"","favicon":{"url":"https:\/\/x-theme.net\/avas-blog\/wp-content\/uploads\/sites\/42\/2019\/12\/icon-blog.png","id":"617","height":"20","width":"20","thumbnail":"https:\/\/x-theme.net\/avas-blog\/wp-content\/uploads\/sites\/42\/2019\/12\/icon-blog.png","title":"icon-blog","caption":"","alt":"","description":""},"mob_version":"1","preloader":"0","preloader-bg-color":"","preloader-color":"","selection-bg-color":"","selection-text-color":"","page-layout":"full-width","body-background":{"background-color":"","background-repeat":"","background-size":"","background-attachment":"","background-position":"","background-image":"","media":{"id":"","height":"","width":"","thumbnail":""}},"wrap-background":{"background-color":"","background-repeat":"","background-size":"","background-attachment":"","background-position":"","background-image":"","media":{"id":"","height":"","width":"","thumbnail":""}},"wrap-margin":{"margin-top":"0","margin-right":"","margin-bottom":"0","margin-left":"","units":"px"},"wrap-padding":{"padding-top":"","padding-right":"","padding-bottom":"","padding-left":"","units":"px"},"wrap-border-top":{"border-top":"0px","border-right":"0px","border-bottom":"0px","border-left":"0px","border-style":"solid","border-color":""},"body":"","link-color":"","link-hover-color":"#b79661","h1-color":"","h2-color":"","h3-color":"","h4-color":"","h5-color":"","h6-color":"","typography-body":{"font-family":"","font-options":"","google":"1","font-weight":"","font-style":"","subsets":"","text-transform":"","font-size":"","line-height":""},"typography-h1":{"font-family":"","font-options":"","google":"1","font-weight":"","font-style":"","subsets":"","text-transform":"","font-size":"","line-height":"","word-spacing":"","letter-spacing":""},"typography-h2":{"font-family":"","font-options":"","google":"1","font-weight":"","font-style":"","subsets":"","text-transform":"","font-size":"","line-height":"","word-spacing":"","letter-spacing":""},"typography-h3":{"font-family":"","font-options":"","google":"1","font-weight":"","font-style":"","subsets":"","text-transform":"","font-size":"","line-height":"","word-spacing":"","letter-spacing":""},"typography-h4":{"font-family":"","font-options":"","google":"1","font-weight":"","font-style":"","subsets":"","text-transform":"","font-size":"","line-height":"","word-spacing":"","letter-spacing":""},"typography-h5":{"font-family":"","font-options":"","google":"1","font-weight":"","font-style":"","subsets":"","text-transform":"","font-size":"","line-height":"","word-spacing":"","letter-spacing":""},"typography-h6":{"font-family":"","font-options":"","google":"1","font-weight":"","font-style":"","subsets":"","text-transform":"","font-size":"","line-height":"","word-spacing":"","letter-spacing":""},"tx_logo":{"url":"https:\/\/x-theme.net\/avas-blog\/wp-content\/uploads\/sites\/42\/2019\/12\/logo-blog.png","id":"529","height":"50","width":"150","thumbnail":"https:\/\/x-theme.net\/avas-blog\/wp-content\/uploads\/sites\/42\/2019\/12\/logo-blog.png","title":"logo-blog","caption":"","alt":"","description":""},"logo-resize":"0","logo_space":{"padding-top":"","padding-right":"","padding-bottom":"","padding-left":"","units":"px"},"header-layout":"boxed","header_overlay":"0","sticky_header":"1","sticky_main_header":"0","sticky_top_header":"0","header_on_off":"1","main_header_margin_home":{"margin-top":"","margin-right":"","margin-bottom":"","margin-left":"","units":"px"},"main_header_padding":{"padding-top":"","padding-right":"","padding-bottom":"","padding-left":"","units":"px"},"header-select":"header2","banner-bussiness-switch":"1","h_ads_switch":"1","head_ad_banner":{"url":"https:\/\/x-theme.net\/avas-blog\/wp-content\/themes\/avas\/assets\/images\/728x90.jpg","id":"","height":"","width":"","thumbnail":"","title":"","caption":"","alt":"","description":""},"head_ad_banner_link":"","head_ad_banner_link_new_window":"0","head_ad_js":"","head_ads_space":{"margin-top":"","margin-right":"","margin-bottom":"","margin-left":"","units":"px"},"bs-info":[{"title":"","description":"","url":"","sort":"0","attachment_id":"","thumb":"","image":"","height":"","width":""}],"head_binfo_space":{"padding-top":"","padding-right":"","padding-bottom":"","padding-left":"","units":"px"},"bs-info-title-color":"","bs-info-desc-color":"","bs-info-sep-color":"","typography-bs-info-title":{"font-family":"","font-options":"","google":"1","font-weight":"","font-style":"","subsets":"","text-align":"","text-transform":"","font-size":"","line-height":"","word-spacing":"","letter-spacing":""},"typography-bs-info-desc":{"font-family":"","font-options":"","google":"1","font-weight":"","font-style":"","subsets":"","text-align":"","text-transform":"","font-size":"","line-height":"","word-spacing":"","letter-spacing":""},"header-bg":{"background-repeat":"","background-size":"","background-attachment":"","background-position":"","background-image":"","media":{"id":"","height":"","width":"","thumbnail":""}},"main_head_bg_color_home":{"color":"","alpha":"1","rgba":""},"sticky_head_bg_color_home":{"color":"","alpha":"1","rgba":""},"main_head_bg_color_inner":{"color":"","alpha":"1","rgba":""},"sticky_head_bg_color_inner":{"color":"","alpha":"1","rgba":""},"main_head_bg_color_container":{"color":"","alpha":"1","rgba":""},"main_head_border":{"border-top":"","border-right":"","border-bottom":"","border-left":"","border-style":"solid","border-color":""},"main_head_border_color":{"color":"","alpha":"1","rgba":""},"top_head":"1","top_head_space":{"padding-top":"","padding-right":"","padding-bottom":"","padding-left":"","units":"px"},"wm_switch":"0","welcome_msg":"Welcome to Avas WordPress Theme.","welcome_msg_color":"","typography-welcome-msg":{"font-family":"","font-options":"","google":"1","font-weight":"","font-style":"","subsets":"","text-align":"","text-transform":"","font-size":"","line-height":"","word-spacing":"","letter-spacing":""},"tx-date":"0","date-color":"","tx-phone":"1","phone-number":"+1 229-226-7070","phone-color":"","tx-email":"1","email-address":"info@website.com","email-color":"","news_ticker":"0","newsticker-posts-per-page":"5","news_ticker_bar_text":"Trending","news-ticker-title-color":"","news-ticker-title-hover":"","tx_news_ticker_bar":"","tx_news_ticker_bar_color":"","tx_news_ticker_nav_color":"","tx_news_ticker_nav_border_color":"","tx_news_ticker_nav_hover_color":"","tx_news_ticker_nav_background_hover_color":"","tx_news_ticker_nav_border_hover_color":"","top_menu":"0","top-menu-link-color":"","top-menu-link-hover-color":"","login_reg":"0","login-register":"Login","signup-text":"my-account","login-link-color":"","login-link-hover-color":"","login-form-btn-color":"","login-form-btn-hov-color":"","social_buton_top":"1","social-media-icon-header-color":"#555555","social-media-icon-header-hover-color":"#b79661","top_head_bg_color_home":{"color":"","alpha":"1","rgba":""},"top_head_bg_color_inner":{"color":"#ffffff","alpha":"1","rgba":"rgba(255,255,255,1)"},"top_head_border":{"border-top":"1px","border-right":"1px","border-bottom":"1px","border-left":"1px","border-style":"solid","border-color":""},"top_head_border_color":{"color":"#e9e9e9","alpha":"1","rgba":"rgba(233,233,233,1)"},"typography-top-header":{"font-family":"","font-options":"","google":"1","font-weight":"","font-style":"","text-align":"","text-transform":"","font-size":"","line-height":"","word-spacing":"","letter-spacing":""},"sub-header-switch":"1","sub_h_title":"1","sub_h_post_title":{"page":"1","post":"1","archive":"1"},"breadcrumbs":"1","sub_h_post_breadcrumbs":{"page":"1","post":"1","archive":"1"},"sub_h_space":{"padding-top":"50px","padding-right":"","padding-bottom":"50px","padding-left":"","units":"px"},"sub-header-title-color":"","sub-header-link-color":"","sub-header-link-hover-color":"#b79661","sub-header-separate-color":"#b7b7b7","sub-header-active-link-color":"#b7b7b7","sub-header-bg":{"background-color":"#343a40","background-repeat":"","background-size":"","background-attachment":"","background-position":"","background-image":"","media":{"id":"","height":"","width":"","thumbnail":""}},"typography-sub-header":{"font-family":"","font-options":"","google":"1","font-weight":"","font-style":"","subsets":"","text-align":"","text-transform":"","font-size":"","line-height":"","word-spacing":"","letter-spacing":""},"typography-breadcrumbs":{"font-family":"","font-options":"","google":"1","font-weight":"","font-style":"","subsets":"","text-align":"","text-transform":"","font-size":"","line-height":"","word-spacing":"","letter-spacing":""},"menu-left-width":{"width":"","units":"%"},"menu-right-width":{"width":"","units":"%"},"menu-alignment":"none","menu_padding":{"padding-top":"12px","padding-right":"15px","padding-bottom":"12px","padding-left":"15px","units":"px"},"menu-border":{"border-top":"1px","border-right":"1px","border-bottom":"1px","border-left":"1px","border-style":"solid","border-color":"#e9e9e9"},"menu_bar_bg_color_home":{"alpha":"1"},"menu_bar_bg_color_inner":{"color":"","alpha":"1","rgba":""},"menu-link-color":"","menu-link-color-home":"","menu-link-hover-color":"#b79661","menu-link-hover-color-home":"","menu-active-link-color":"","menu-active-link-color-home":"","menu-link-bg-hover-color":"","menu-link-bg-hover-color-home":"","menu-active-link-bg-color":"","menu-active-link-bg-color-home":"","sub-menu-bg-color":"","sub-menu-link-color":"","sub-menu-link-hover-color":"","sub-menu-border-color":"","mega-menu-columns-border":{"border-top":"","border-right":"","border-bottom":"","border-left":"","border-style":"solid","border-color":""},"mega-menu-columns-title-color":"","menu-font":{"font-family":"","font-options":"","google":"1","font-weight":"","font-style":"","subsets":"","text-align":"","text-transform":"","font-size":"","line-height":"","word-spacing":"","letter-spacing":""},"sub-menu-font":{"font-family":"","font-options":"","google":"1","font-weight":"","font-style":"","subsets":"","text-align":"","text-transform":"","font-size":"","line-height":"","word-spacing":"","letter-spacing":""},"menu-dropdown-icon":"0","menu-dropdown-icon-valign":"0","menu_item_border":"0","menu_item_border_select":"menu_item_border_top","menu-top-border-hover-color":"","menu-item-seprator":"1","menu-item-seprator-border":{"border-top":"1px","border-right":"1px","border-bottom":"1px","border-left":"1px","border-style":"solid","border-color":"#e9e9e9"},"mobile-top-menu-icon-color":"","mobile-menu-icon-color":"","mobile-menu-border-color":"","menu_btn_switch":"0","menu_btn_txt":"Button","menu_btn_url":"#","menu_btn_link_new_window":"0","menu_btn_padding":{"padding-top":"","padding-right":"","padding-bottom":"","padding-left":"","units":"px"},"menu_btn_margin":{"margin-top":"","margin-right":"","margin-bottom":"","margin-left":"","units":"px"},"menu-btn-bg-color":"","menu-btn-bg-hov-color":"","menu-btn-color":"","menu-btn-hov-color":"","menu-btn-border":{"border-top":"","border-right":"","border-bottom":"","border-left":"","border-style":"solid","border-color":""},"menu-btn-bord-color":"","menu-btn-bord-hov-color":"","menu-btn-font":{"font-family":"","font-options":"","google":"1","font-weight":"","font-style":"","subsets":"","text-align":"","text-transform":"","font-size":"","line-height":"","word-spacing":"","letter-spacing":""},"tx-cart":"0","tx-cart_space":{"margin-top":"","margin-right":"","margin-bottom":"","margin-left":"","units":"px"},"tx-cart-icon-color":"","tx-cart-icon-hover-color":"","search":"1","search_space":{"margin-top":"","margin-right":"","margin-bottom":"","margin-left":"","units":"px"},"search-icon-color":"","search-icon-hover-color":"#b79661","search-icon-close-color":"","search-icon-close-hover-color":"#b79661","side_menu":"1","side_menu_margin":{"margin-top":"","margin-right":"","margin-bottom":"","margin-left":"","units":"px"},"side-menu-icon-color":"","side-menu-icon-color-hover":"#b79661","side-menu-icon-close-color":"","side-menu-icon-close-color-hover":"","side-menu-bg-color":"","side-menu-text-color":"","side-menu-link-color":"","side-menu-link-hover-color":"","side-menu-widget-title-color":"","side-menu-icon-font":{"font-family":"","font-options":"","google":"1","font-weight":"","font-style":"","font-size":"","line-height":""},"side-menu-font":{"font-family":"","font-options":"","google":"1","font-weight":"","font-style":"","subsets":"","text-align":"","text-transform":"","font-size":"","line-height":"","word-spacing":"","letter-spacing":""},"side-menu-text-font":{"font-family":"","font-options":"","google":"1","font-weight":"","font-style":"","subsets":"","text-align":"","text-transform":"","font-size":"","line-height":"","word-spacing":"","letter-spacing":""},"side-menu-widget-title-font":{"font-family":"","font-options":"","google":"1","font-weight":"","font-style":"","subsets":"","text-align":"","text-transform":"","font-size":"","line-height":"","word-spacing":"","letter-spacing":""},"sidebar-select":"sidebar-right","sidebar-single":"sidebar-right","cat_temp_style":"cat_style_3","title-length":"55","excerpt-word-limit":"25","blog-posts-per-page":"9","cat_limit":"8","tag_limit":"15","read-more":"1","read-more-text":"Read More","post-time":"1","post-author":"1","post-comment":"1","post-views":"1","social-share-header":"1","featured-image":"1","posts-title":"1","post-category":"1","post-tag":"1","social-share-footer":"1","related-posts":"1","prev-next-posts":"1","comments-posts":"1","posts-title-color":"","post-title-hover-color":"#b79661","posts-text-color":"","post_meta_icon_color":"#b79661","post_meta_text_color":"","post_meta_text_hov_color":"","posts-date-color":"","posts-date-bg-color":"#b79661","posts-date-hov-color":"","posts-date-bg-hov-color":"#b7822c","posts-bottom-border-hov-color":"#b79661","posts-read-more-btn-color":"#ffffff","posts-read-more-btn-bg-color":"#343a40","posts-read-more-btn-hov-color":"","single-posts-title-color":"","single-posts-text-color":"","related-post-bar-bg-color":"#343a40","related-post-bar-title-color":"","related-post-overlay-color":"#b79661","related-post-title-color":"","next-prev-post-color":"","next-prev-post-bg-color":"","next-prev-post-hov-color":"#ffffff","next-prev-post-bg-hov-color":"#343a40","author-bg-color":"","post_comment_form_btn_color":"","post_comment_form_btn_hov_color":"","post_comment_form_btn_bg_color":"#b79661","post_comment_form_btn_bg_hov_color":"#343a40","form-control-focus":"#b79661","posts-title-font":{"font-family":"","font-options":"","google":"1","font-weight":"","font-style":"","subsets":"","text-align":"","text-transform":"","font-size":"","line-height":"","word-spacing":"","letter-spacing":""},"posts-paragraph-font":{"font-family":"","font-options":"","google":"1","font-weight":"","font-style":"","subsets":"","text-align":"","text-transform":"","font-size":"","line-height":"","word-spacing":"","letter-spacing":""},"posts-blockquote-font":{"font-family":"","font-options":"","google":"1","font-weight":"","font-style":"","subsets":"","text-align":"","text-transform":"","font-size":"","line-height":"","word-spacing":"","letter-spacing":""},"sidebar-bg-color":"","sidebar-border-color":"","sidebar-title-color":"","sidebar-title-border-color":"","sidebar-title-border-after-color":"#b79661","sidebar-search-icon-color":"","sidebar-search-icon-hover-color":"#b79661","sidebar-category-color":"","sidebar-category-hover-color":"#b79661","sidebar-title-font":{"font-family":"","font-options":"","google":"1","font-weight":"","font-style":"","subsets":"","text-align":"","text-transform":"","font-size":"","line-height":"","word-spacing":"","letter-spacing":""},"sidebar-recent-posts-title-font":{"font-family":"","font-options":"","google":"1","font-weight":"","font-style":"","subsets":"","text-align":"","text-transform":"","font-size":"","line-height":"","word-spacing":"","letter-spacing":""},"post_ads":"0","s_ads_switch":"1","s_ad_banner":{"url":"https:\/\/x-theme.net\/avas-blog\/wp-content\/themes\/avas\/assets\/images\/300x250.jpg","id":"","height":"","width":"","thumbnail":"","title":"","caption":"","alt":"","description":""},"s_ad_banner_link":"","s_ad_js":"","service_post_type":"0","services_title":"Services","service-slug":"service","service-cat-slug":"service-category","service-overlay-color":{"color":"","alpha":"1","rgba":""},"service-title-color":"","service-title-hov-color":"","service-title-holder-bg-color":{"color":"","alpha":"1","rgba":""},"service-content-bg-color":"","service-excerpt-color":"","service-excerpt-overlay-color":"","service-cat-color":"","service-cat-hov-color":"","service-overlay-icon-color":"","service-overlay-icon-hov-color":"","service-download-btn-color":"","service-download-btn-bg-color":"","service-download-btn-txt-hov-color":"","service-download-btn-bg-hov-color":"","portfolio_post_type":"0","portfolio-time":"1","portfolio-author":"1","portfolio-meta-color-left":"","portfolio-meta-color-right":"","portfolio-meta-link-color":"","portfolio-meta-link-hover-color":"","portfolio_title":"Portfolio","portfolio-slug":"portfolio","portfolio-cat-slug":"portfolio-category","portfolio-project-details-bg-color":"","portfolio-project-details-br-color":"","portfolio-project-completion-progressbar-color":"","portfolio-item-overlay-bg-color":{"color":"","alpha":"1","rgba":""},"team_post_type":"0","team-per-page":"12","team_skill":"1","team-profile-skill-bar-color":"","project_experience":"1","project_experience_title":"Project Experience","project-exp-count":"8","team-project-overlay-bg-color":"","team_social_profile":"1","pagination-team":"1","team-profile-pic-border":{"border-top":"0px","border-right":"0px","border-bottom":"0px","border-left":"0px","border-style":"solid","border-color":"#dfdfdf"},"team-hire-border":{"border-top":"","border-right":"","border-bottom":"","border-left":"","border-style":"solid","border-color":"#fff"},"team_title":"Team","team-slug":"team","team-cat-slug":"team-category","team-overlay-bg-color":"","team-name-color":"","team-name-hov-color":"","team-cat-color":"","team-cat-hov-color":"","team-bio-color":"","team-social-icon-color":"","team-social-icon-hov-color":"","team-profile-pic-bg-color":"","team-profile-button-color":"","team-profile-button-hov-color":"","social":"1","behance":"","facebook":"https:\/\/www.facebook.com\/avas.wordpress.theme\/","flickr":"","github":"","instagram":"","linkedin":"#","pinterest":"","qq":"","reddit":"","skype":"","snapchat":"","soundcloud":"","spotify":"","stumbleupon":"","telegram":"","tumblr":"","twitch":"","twitter":"https:\/\/twitter.com\/AvasTheme","vimeo":"","vine":"","vk":"","whatsapp":"","wikipedia":"","xing":"","yelp":"","youtube":"https:\/\/www.youtube.com\/channel\/UC1hlWYgndZw7PEHWeTbYvfA","social-media-icon-shortcode-color":"#ffffff","social-media-icon-shortcode-color-hover":"#b79661","social_share_bg_clr":"","social_share_border_clr":"","social-share-title-color":"","footer_top":"1","footer_bg":{"background-color":"","background-repeat":"","background-size":"","background-attachment":"","background-position":"","background-image":"","media":{"id":"","height":"","width":"","thumbnail":""}},"footer-text-color":"","footer-link-color":"","footer-link-hover-color":"","footer-widget-title-color":"","footer-top-fonts":{"font-family":"","font-options":"","google":"1","font-weight":"","font-style":"","subsets":"","text-align":"","text-transform":"","font-size":"","line-height":"","word-spacing":"","letter-spacing":""},"footer-widget":{"font-family":"","font-options":"","google":"1","font-weight":"","font-style":"","subsets":"","text-align":"","text-transform":"","font-size":"","line-height":"","word-spacing":"","letter-spacing":""},"footer_layout":"boxed","footer_cols":"3","footer_top_space":{"padding-top":"","padding-right":"","padding-bottom":"","padding-left":"","units":"px"},"footer-top-widget-alignment":"left","footer_top_widget_margin":{"margin-top":"","margin-right":"","margin-bottom":"","margin-left":"","units":"px"},"footer_bottom":"1","footer-select":"footer2","footer-bottom-bg-color":"","footer-border-color":"","footer-menu":"0","footer-menu-color":"","footer-menu-hover-color":"","footer-menu-separator-color":"","footer-menu-font":{"font-family":"","font-options":"","google":"1","font-weight":"","font-style":"","subsets":"","text-align":"","text-transform":"","font-size":"","line-height":"","word-spacing":"","letter-spacing":""},"social_icons_footer":"0","social-media-icon-footer-color":"","social-media-icon-footer-color-hover":"","back_top":"1","back_top_bg":"","back_top_bg_hover":"","back_top_border":"","back_top_border_hover":"","back_top_icon":"","back_top_icon_hover":"","copyright":"Copryright &copy; 2019, By <a href=\"https:\/\/themeforest.net\/user\/theme-x\">theme-x<\/a> | All rights reserved.","footer-copyright-text-color":"","footer-copyright-link-color":"","footer-copyright-link-hover-color":"","footer-copyright":{"font-family":"","font-options":"","google":"1","font-weight":"","font-style":"","subsets":"","text-align":"","text-transform":"","font-size":"","line-height":"","word-spacing":"","letter-spacing":""},"contact_form_button_bg_color":"#343a40","contact_form_button_bg_hov_color":"#b79661","contact_form_button_border_color":"","contact_form_button_color":"","contact_form_button_hover_color":"","contact_form_button_border_color_hover":"","contact_form_fields_border_color":"","pagination_space":{"padding-top":"","padding-right":"","padding-bottom":"","padding-left":"","units":"px"},"pagination_bg_color":"","pagination_bg_hover_color":"","pagination_active_bg_color":"","pagination_color":"","pagination_hover_color":"","pagination_active_color":"","instagram_api":"6896066625.1677ed0.cdbec3dedd9b40398e6f321b3fbed647","custom_css":"@media(max-width:767px){\r\n.social_media{float:none;padding-left:0}\r\n}","custom_js_head":"","custom_js_footer":"","s_ads_after_p":1,"author-bio-posts":1,"redux-backup":"1"}